pyatomix/__init__.py
pyatomix-0.1.0.dist-info/LICENSE
pyatomix-0.1.0.dist-info/METADATA
pyatomix-0.1.0.dist-info/WHEEL
pyatomix-0.1.0.dist-info/top_level.txt
pyatomix-0.1.0.dist-info/RECORD
