Metadata-Version: 2.2
Name: pyatomix
Version: 0.1.0
Summary: Cross platform atomic int for Python
Maintainer-email: 0xDEADFED5 <admin@terminoid.com>
License: BSD
Project-URL: Homepage, https://github.com/0xDEADFED5/pyatomix
Project-URL: Github, https://github.com/0xDEADFED5/pyatomix
Keywords: atomic,atomics,free-threading,no-GIL
Classifier: Programming Language :: Python :: 3 :: Only
Classifier: Programming Language :: Python :: 3.10
Classifier: Programming Language :: Python :: 3.11
Classifier: Programming Language :: Python :: 3.12
Classifier: Programming Language :: Python :: 3.13
Classifier: Development Status :: 5 - Production/Stable
Classifier: License :: OSI Approved :: BSD License
Classifier: Intended Audience :: Developers
Classifier: Operating System :: MacOS
Classifier: Operating System :: Microsoft :: Windows
Classifier: Operating System :: POSIX :: Linux
Classifier: Topic :: Software Development :: Libraries :: Application Frameworks
Requires-Python: >=3.7
License-File: LICENSE
Requires-Dist: atomix_base>=0.1.0
